{
  "leaks": [
    {
      "source": "Acrimed",
      "date": "28 avril 2026",
      "description": "Adresse emailMot de passe chiffré (🤷)Commandes passées"
    },
    {
      "source": "Agence de Services et de Paiement",
      "date": "27 avril 2026",
      "description": "Nom, prénomNuméro de sécurité socialeAdresse postaleAvis de paiementIBAN"
    },
    {
      "source": "Système U",
      "date": "24 avril 2026",
      "description": "Nom, prénomStatus professionelAdresse emailAdresse postaleNuméro de téléphoneNuméro de la carte de f..."
    }
  ],
  "opensource": [
    {
      "name": "Explore",
      "category": "Open Source",
      "description": "Projet en tendance sur la plateforme."
    },
    {
      "name": "Legal",
      "category": "Open Source",
      "description": "Projet en tendance sur la plateforme."
    },
    {
      "name": "🚀 Just Launched",
      "category": "Open Source",
      "description": "Projet en tendance sur la plateforme."
    }
  ]
}